[
    {
        "name": "cs",
        "authPassword": "Dig3st0f7H3d347h"
    },
    {
        "name": "s",
        "authPassword": "Dig3st0f7H3d347h"
    },
    {
        "name": "colbi",
        "authPassword": "Dig3st0f7H3d347h"
    },
    {
        "name": "covelli",
        "authPassword": "Dig3st0f7H3d347h"
    },
    {
        "name": "test",
        "authPassword": "Dig3st0f7H3d347h"
    },
    {
        "name": "col",
        "authPassword": "Dig3st0f7H3d347h"
    },
    {
        "name": "allo",
        "authPassword": "Dig3st0f7H3d347h"
    },
    {
        "name": "Vgg",
        "authPassword": "Dig3st0f7H3d347h"
    },
    {
        "name": "Uu",
        "authPassword": "Dig3st0f7H3d347h"
    },
    {
        "name": "coco",
        "authPassword": "Dig3st0f7H3d347h"
    },
    {
        "name": "Coco",
        "authPassword": "Dig3st0f7H3d347h"
    },
    {
        "name": "tets",
        "authPassword": "Dig3st0f7H3d347h"
    },
    {
        "name": "T",
        "authPassword": "Dig3st0f7H3d347h"
    },
    {
        "name": "tata",
        "authPassword": "Dig3st0f7H3d347h"
    },
    {
        "name": "demo",
        "authPassword": "Dig3st0f7H3d347h"
    },
    {
        "name": "",
        "authPassword": "Dig3st0f7H3d347h"
    },
    {
        "name": "cff",
        "authPassword": "Dig3st0f7H3d347h"
    }
]